{
  "id": "8726f5a0-3ac9-4495-b877-68ec4edca97e",
  "alias": "MyToolsApplicationCustomizer",
  "componentType": "Extension",
  "extensionType": "ApplicationCustomizer",
  "version": "0.0.1",
  "manifestVersion": 2,
  "requiresCustomScript": false,
  "loaderConfig": {
    "internalModuleBaseUrls": [
      "https://localhost:4321/dist/"
    ],
    "entryModuleId": "my-tools-application-customizer",
    "scriptResources": {
      "my-tools-application-customizer": {
        "type": "path",
        "path": "my-tools-application-customizer.js"
      },
      "@microsoft/sp-dialog": {
        "type": "component",
        "id": "c0c518b8-701b-4f6f-956d-5782772bb731",
        "version": "1.17.3"
      },
      "MyToolsApplicationCustomizerStrings": {
        "type": "path",
        "path": "MyToolsApplicationCustomizerStrings_en-us.js"
      },
      "@microsoft/sp-application-base": {
        "type": "component",
        "id": "4df9bb86-ab0a-4aab-ab5f-48bf167048fb",
        "version": "1.17.3"
      },
      "@microsoft/sp-core-library": {
        "type": "component",
        "id": "7263c7d0-1d6a-45ec-8d85-d4d1d234171b",
        "version": "1.17.3"
      }
    }
  }
}